lectocal/__init__.py
lectocal/client_secret.json
lectocal/gauth.py
lectocal/gcalendar.py
lectocal/lectio.py
lectocal/lesson.py
lectocal/run.py
lectocal-1.2.1.dist-info/METADATA
lectocal-1.2.1.dist-info/RECORD
lectocal-1.2.1.dist-info/WHEEL
lectocal-1.2.1.dist-info/entry_points.txt
lectocal-1.2.1.dist-info/top_level.txt
