Metadata-Version: 2.1
Name: lectocal
Version: 1.2.1
Summary: Syncronize Lectio schedules to Google Calendar.
Home-page: https://github.com/Hanse00/LecToCal
Author: Philip 'Hanse00' Mallegol-Hansen
Author-email: philip@mallegolhansen.com
License: Apache 2.0
Keywords: lectio google calendar sync utility
Platform: UNKNOWN
Classifier: Development Status :: 5 - Production/Stable
Classifier: Intended Audience :: Education
Classifier: Intended Audience :: End Users/Desktop
Classifier: Topic :: Education
Classifier: Topic :: Utilities
Classifier: Topic :: Office/Business :: Scheduling
Classifier: Programming Language :: Python :: 3 :: Only
Classifier: Programming Language :: Python :: 3.5
Classifier: Programming Language :: Python :: 3.6
Classifier: Programming Language :: Python :: 3.7
Classifier: Environment :: No Input/Output (Daemon)
Classifier: Environment :: Web Environment
Classifier: License :: OSI Approved :: Apache Software License
Requires-Python: >=3
Requires-Dist: google-api-python-client
Requires-Dist: requests
Requires-Dist: lxml
Requires-Dist: pytz
Requires-Dist: python-dateutil
Requires-Dist: oauth2client
